{"data":{"lastBuildDate":"Wed, 04 Feb 2026 10:09:54 +0900","total":1,"start":1,"display":1,"items":[{"title":"우포늪엔 공룡 똥구멍이 있다 (제1회 푸른문학상 수상작)","link":"https://search.shopping.naver.com/book/catalog/32540609796","image":"https://shopping-phinf.pstatic.net/main_3254060/32540609796.20221228073822.jpg","author":"손호경","discount":"10620","publisher":"푸른책들","pubdate":"20160930","isbn":"9788988578995","description":"우포늪 언저리에서 태어나고 자란 작가의 생생한 체험과 자연 생태적 특성이 잘 반영된 장편동화. 우포늪 전체를 거대한 공룡으로 보고 이를 굳게 믿는 동심을 그림으로써 동화 속의 공간을 상징적이며 주술적인 힘에 휩싸이게 한다. 본문 곳곳에 삽입된 우포늪 주변 생물들의 세밀화가 우포늪을 보다 생생하게 느끼게 해 준다. 제1회 푸른문학상 '미래의 작가상' 부문 수상작."}]},"timestamp":1770167394417}