{"data":{"lastBuildDate":"Tue, 03 Feb 2026 15:46:45 +0900","total":17,"start":1,"display":5,"items":[{"title":"<b>4줄요약독해</b>: <b>전래동화</b>&gt; <b>4줄로 요약하는 초등 문해력 기본서</b>","link":"https://blog.naver.com/ms1224/223780263850","description":"어린이첫<b>독해</b> 문제집 &lt;<b>4줄요약독해</b>: <b>전래동화</b>&gt; <b>4줄로 요약하는 초등 문해력 기본서</b> 그 어느 때보다... <b>4줄 요약독해</b>: <b>전래동화</b> 저자 <b>이젠국어연구소</b> 출판 이젠교육 발매 2025.01.10. 이젠교육의 &lt;<b>4줄 요약독해</b>... ","bloggername":"비바저널 : 책과 일상, 엄마의 교육 & 취미 기록","bloggerlink":"blog.naver.com/ms1224","postdate":"20250302"},{"title":"<b>4줄요약독해 전래동화</b> <b>4줄로 요약하는 초등문해력 기본서</b>","link":"https://blog.naver.com/235785/223807047888","description":"이젠교육:) <b>4줄요약독해 전래동화</b> <b>4줄로 요약하는 초등문해력 기본서</b> 첫 페이지를 펼치면 <b>전래동화</b>... 있어서 <b>초등</b> 저학년 친구들에게 추천해요~~ <b>4줄 요약독해</b>: <b>전래동화</b> 저자 <b>이젠국어연구소</b> 출판... ","bloggername":"책놀이하는쪼쪼맘입니다:)","bloggerlink":"blog.naver.com/235785","postdate":"20250323"},{"title":"<b>초등 문해력 기본서 4줄요약독해</b> - <b>전래동화</b>","link":"https://blog.aladin.co.kr/778839144/16325569","description":"<b>4줄 요약독해 전래동화 - 4줄로 요약하는 초등 문해력 기본서</b> ㅣ <b>4줄 요약독해</b> 시리즈 <b>이젠국어연구소</b> 지음 / 이젠교육 / 2025년 1월 평점 : <b>4줄로 요약하는 초등 문해력 기본서 4줄 요약 독해 전래동화</b> 입니다 발단... ","bloggername":"[슈리님의 서재] : 알라딘","bloggerlink":"https://blog.aladin.co.kr/778839144","postdate":"20250324"},{"title":"이젠교육 ▶ <b>4줄 요약 독해</b> - <b>전래동화</b>","link":"https://blog.naver.com/quineka/223807881797","description":"<b>4줄 요약 독해</b> : <b>전래동화</b> <b>4줄로 요약하는 초등 문해력 기본서</b> 지은이. <b>이젠국어연구소</b> 출판. 이젠교육 <b>4줄 요약독해</b>: <b>전래동화</b> 저자 <b>이젠국어연구소</b> 출판 이젠교육 발매 2025.01.10. 말하기 놀이카드가 <b>전래동화</b>에... ","bloggername":"세남매와 달팽이맘의 생활","bloggerlink":"blog.naver.com/quineka","postdate":"20250324"},{"title":"<b>4줄 요약독해</b> _<b>전래동화</b> <b>4줄로 요약하는 초등 문해력 기본서</b>","link":"https://blog.aladin.co.kr/726109200/16300551","description":"<b>4줄 요약독해 전래동화 - 4줄로 요약하는 초등 문해력 기본서</b> ㅣ <b>4줄 요약독해</b> 시리즈 <b>이젠국어연구소</b>... <b>요약독해</b> #국어<b>독해</b> #<b>독해</b><b>기본서</b> #어린이첫<b>독해</b> #이야기책 #<b>초등</b>저학년<b>독해</b>추천 #책읽기 #글쓰기 #<b>동화</b>... ","bloggername":"[wjdsj3님의 서재] : 알라딘","bloggerlink":"https://blog.aladin.co.kr/726109200","postdate":"20250314"}]},"timestamp":1770101205783}