{"data":{"lastBuildDate":"Mon, 02 Feb 2026 22:41:05 +0900","total":1,"start":1,"display":1,"items":[{"title":"에그박사와 공룡 에그","link":"https://search.shopping.naver.com/book/catalog/43743720622","image":"https://shopping-phinf.pstatic.net/main_4374372/43743720622.20231102092113.jpg","author":"최설희","discount":"13050","publisher":"미래엔아이세움","pubdate":"20231108","isbn":"9791168416611","description":"에그박사와 함께 떠나는 공룡 시대 대모험!\n\n《에그박사와 공룡 에그》는 인기 키즈 크리에이터 ‘에그박사’의 새로운 공룡 학습 만화입니다. 공룡 화석을 조사하던 중, 갑작스레 공룡 시대에 떨어진 에그박사 일행은 정체불명의 아기 공룡 ‘에그’의 탄생을 목격하게 되지요. 과연 이들은 에그의 가족을 찾아 주고 집으로 무사히 돌아갈 수 있을까요? 에그박사 일행의 좌충우돌 공룡 시대 탐험기를 재미있는 만화로 읽고, 공룡에 대한 다양한 정보도 얻어 보세요!  \n\n자연·생물 콘텐츠 인기 키즈 크리에이터, ‘에그박사’\n‘에그박사’는 자극적인 콘텐츠가 넘치는 미디어 시장에서 보다 더 유익한 영상을 만들고자 노력하는 자연·생물 콘텐츠 크리에이터입니다. 에그박사와 양박사, 웅박사가 모여 도시에서 쉽게 만날 수 없는 신기한 생물들을 생생하고 재미있는 영상 콘텐츠로 풀어 내어 자연 생물에 호기심이 가득한 어린이들에게 많은 사랑을 받고 있습니다."}]},"timestamp":1770039665404}