{"data":{"lastBuildDate":"Tue, 03 Feb 2026 15:10:47 +0900","total":45,"start":1,"display":5,"items":[{"title":"<b>불량가족레시피</b>,성장소설, <b>문학동네청소년문학상 대상수상작</b>~!!","link":"https://blog.naver.com/96427893/222060800041","description":"<b>불량가족레시피</b> <b>제1회 문학동네청소년문학상 대상 수상작 손현주</b> 소설 사실 가출은 충동적으로 나가는... ^^유쾌한, <b>불량가족레시피</b> 추천해요~ <b>불량 가족 레시피</b> 작가 <b>손현주</b> 출판 <b>문학동네</b> 발매 2011.01.24. 평점... ","bloggername":"★수민&민재 오늘도맑음~★","bloggerlink":"blog.naver.com/96427893","postdate":"20200831"},{"title":"<b>문학동네 청소년문학상 대상수상작</b> (1)","link":"https://blog.naver.com/bookprice_/222837376655","description":"<b>손현주</b> (지은이)<b>문학동네</b>2011-01-24 https://www.bookprice.co.kr/compare.jsp?isbn=9788954613873 <b>문학동네 청소년</b> 시리즈 6권. <b>제1회 문학동네청소년문학상 대상 수상작</b>. 원조 콩가루 집안이라 할 수 있는 위태로운 한 <b>가족</b>... ","bloggername":"북프라이스","bloggerlink":"blog.naver.com/bookprice_","postdate":"20220802"},{"title":"<b>불량 가족 레시피</b>","link":"https://blog.naver.com/watnymph/80125378037","description":"<b>불량 가족 레시피</b> <b>손현주</b> 지음 <b>문학동네</b> 2011.01.24 평점 <b>불량가족 레시피</b> <b>제1회 문학동네청소년문학상 대상 수상작</b> 권여울을 만나면서 하루 종일 가슴이 답답했다. <b>청소년</b>의 실태를 보여주는 부분에서는 공감도... ","bloggername":"행운의 수정, 산의 속삭임","bloggerlink":"blog.naver.com/watnymph","postdate":"20110227"},{"title":"<b>문학동네 청소년문학상</b>","link":"https://blog.aladin.co.kr/703617131/13954223","description":"보기 <b>불량 가족 레시피- 제1회 문학동네청소년문학상 대상 수상작 손현주</b> 지음 / <b>문학동네</b>... 제2회 <b>문학동네청소년문학상 대상 수상작</b> 마윤제 지음 / <b>문학동네</b> / 2012년 1월 12,000 원 → 10,800... ","bloggername":"[kojkkojk의 서재] : 알라딘","bloggerlink":"https://blog.aladin.co.kr/703617131","postdate":"20220923"},{"title":"<b>불량가족 레시피</b>","link":"https://blog.naver.com/wisdom8187/10157581442","description":"<b>불량 가족 레시피</b> 작가 <b>손현주</b> 출판 <b>문학동네</b> 발매 2011.01.24 제목: <b>불량 가족 레시피</b> (<b>제1회 문학동네청소년문학상 대상 수상작</b>) 저자: <b>손현주</b> 분야: <b>청소년</b>소설 ISBN: 895461387X 9788954613873 출판사: <b>문학동네</b>... ","bloggername":"독서의 환희","bloggerlink":"blog.naver.com/wisdom8187","postdate":"20130121"}]},"timestamp":1770099047597}