{"data":{"lastBuildDate":"Mon, 02 Feb 2026 15:36:11 +0900","total":7,"start":1,"display":5,"items":[{"title":"<b>15소년 안전 표류기 - 위험이 꿈틀대는 모험에서 살아남는 법</b>","link":"https://blog.naver.com/hera_poem/224140769110","description":"《<b>15소년 안전 표류기</b>》는 <b>강승임</b> 글, 허지영 그림, 책속물고기에서 출판한 <b>안전</b> 사고에 대해 알려주는 동화책입니다. '<b>위험이 꿈틀대는 모험에서 살아남는 법</b>'이라는 부제가 붙어 있어요. 이 책은 주인공 마루와... ","bloggername":"sophia","bloggerlink":"blog.naver.com/hera_poem","postdate":"20260109"},{"title":"21차 바로북","link":"https://blog.aladin.co.kr/790851187/16878858","description":"5월 <b>15</b>,000 원 → 13,500 원( 10% 할인) / 마일리지 750 원( 5% 적립) 양탄자배송 내일 아침 7시 출근전 배송 2025년 11월 19일에 저장 <b>15소년 안전 표류기- 위험이 꿈틀대는 모험에서 살아남는 법 강승임</b>... ","bloggername":"[angelic321님의 서재] : 알라딘","bloggerlink":"https://blog.aladin.co.kr/790851187","postdate":"20251116"},{"title":"향동숲내초","link":"https://blog.aladin.co.kr/778573125/16768893","description":"<b>15</b>,000 원 → 13,500 원( 10% 할인) / 마일리지 750 원( 5% 적립) 양탄자배송 내일 아침 7시 출근전 배송 2025년 09월 27일에 저장 <b>15소년 안전 표류기- 위험이 꿈틀대는 모험에서 살아남는 법 강승임</b>... ","bloggername":"[지산님의 서재] : 알라딘","bloggerlink":"https://blog.aladin.co.kr/778573125","postdate":"20250927"},{"title":"사회철학역사","link":"https://blog.aladin.co.kr/795305102/16365952","description":"원 → <b>15</b>,120 원( 10% 할인) / 마일리지 840 원( 5% 적립) 양탄자배송 내일 밤 11시 잠들기전 배송 2025년 04월 08일에 저장 <b>15소년 안전 표류기- 위험이 꿈틀대는 모험에서 살아남는 법 강승임</b> 지음... ","bloggername":"[박알기님의 서재] : 알라딘","bloggerlink":"https://blog.aladin.co.kr/795305102","postdate":"20250408"},{"title":"[완료][풍동 4-2차] 희망(아동)","link":"https://blog.aladin.co.kr/766771184/16403866","description":"<b>15</b>,000 원 → 13,500 원( 10% 할인) / 마일리지 750 원( 5% 적립) 양탄자배송 밤 11시 잠들기전 배송 2025년 04월 25일에 저장 <b>15소년 안전 표류기- 위험이 꿈틀대는 모험에서 살아남는 법 강승임</b>... ","bloggername":"[안나님의 서재] : 알라딘","bloggerlink":"https://blog.aladin.co.kr/766771184","postdate":"20250424"}]},"timestamp":1770014171785}