{"data":{"lastBuildDate":"Wed, 04 Feb 2026 10:10:29 +0900","total":1,"start":1,"display":1,"items":[{"title":"식물 도감 (초등학교 전 학년, 전 과목 교과서에서 뽑은 160가지 식물 이야기)","link":"https://search.shopping.naver.com/book/catalog/32491397936","image":"https://shopping-phinf.pstatic.net/main_3249139/32491397936.20231004072508.jpg","author":"전의식","discount":"22500","publisher":"보리","pubdate":"20160130","isbn":"9788984289024","description":"세밀화로 보는 우리 나라 식물 이야기!\n\n초등학교 전학년, 전 과목 교과서에서 뽑은 160가지 식물이야기『식물 도감: 세밀화로 그린 보리 어린이』. 우리 땅에 뿌리 박고 사는 식물 160종을 세밀화로 담았습니다. ‘세밀화’는 사진 수십 장에 담긴 정보를 한 장으로 압축한 그림으로, 한 생명체의 생김새부터 한살이까지 다양한 정보를 한눈에 살펴볼 수 있습니다. 화가들이 사계절 동안 한 생명체를 관찰하며 섬세하게 그려내어, 개체의 생김새와 특징을 정확하게 보여줍니다. 또한 현장 취재를 바탕으로 생태 정보를 꼼꼼히 담아냈습니다. \n\n초등학교 전 학년, 전 과목 교과서에 나오는 동식물은 물론, 우리 둘레에서 아이들이 흔히 볼 수 있는 생명체들을 두루 실었습니다. 나무에서 얻는 나물들, 기름을 짜는 나무 열매, 약재를 얻는 나무, 집 짓는 데 쓰는 나무, 책상이나 그릇 따위 세간 재료로 쓰는 나무, 종이를 얻거나 염료를 얻는 나무 등, 나무 한 그루를 통해 우리 나라 숲 생태뿐만 아니라 우리 겨레 살림에 어떻게 쓰였는지 상세하게 알 수 있게 하였습니다. \n\n학술적이고 전문적인 정보를 두루 다루면서도 우리 말법에 따라 쉽게 풀어내어 이야기책을 보듯이 술술 읽히는 도감입니다. 여러 동식물들이 어느 곳에서 사는지, 생김새는 어떻고 우리 생활에 어떤 보탬을 주는지에 관한 정보들을 쉽고 재미있게 알 수 있습니다. 이를 통해 자연스럽게 생명에 대한 관심과 애정을 갖게 해 줍니다."}]},"timestamp":1770167429893}