{"data":{"lastBuildDate":"Mon, 02 Feb 2026 22:44:29 +0900","total":1,"start":1,"display":1,"items":[{"title":"눈치코치 삼총사의 눈치껏 배려생활","link":"https://search.shopping.naver.com/book/catalog/51878211627","image":"https://shopping-phinf.pstatic.net/main_5187821/51878211627.20241212092419.jpg","author":"김리하","discount":"11700","publisher":"토끼섬","pubdate":"20241210","isbn":"9791199019706","description":"누구보다 먼저 보고, 누구보다 먼저 마음을 다독이는\n눈치 빠른 어린이들 모이세요!\n\n눈치가 빠르면 얄밉다고요? 여기 눈치 코치 삼총사를 만나면 생각이 바뀔 거예요! \n눈치 코치 삼총사는 빠른 눈치로 누군가의 마음을 빠르게 알아채고, 빠른 발과 빠른 손으로 누군가를 돕고, 보듬는 친구들이거든요. \n눈치 빠른 어린이들, 혹은 눈치는 없지만 다정한 마음만은 누구보다 빠른 어린이들! \n눈치 코치 삼총사와 함께 출동해 봐요. 우리의 다정한 눈치는 세상에 꼭 필요하거든요."}]},"timestamp":1770039869236}