{"data":{"lastBuildDate":"Mon, 02 Feb 2026 14:56:54 +0900","total":7,"start":1,"display":5,"items":[{"title":"[100자평] <b>기적의 한글 학습 2</b>","link":"https://blog.aladin.co.kr/792525120/9370931","description":"<b>기적의 한글 학습 2 - 기본자 학습 2</b>, <b>개정판</b> ㅣ 길벗 <b>기적의</b> <b>학습</b>법 <b>최영환</b> 지음, 천소 그림 / 길벗스쿨 / 2016년 10월 평점 : <b>한글</b>을 좀더 쉽고 재미있게 배울 수 있게 도와 줍니다","bloggername":"[박정남님의 서재] \"책과 통하는 블로그, 알라딘 서재!\"","bloggerlink":"https://blog.aladin.co.kr/792525120","postdate":"20170531"},{"title":"<b>기적의 한글 학습</b>","link":"https://blog.aladin.co.kr/723159102/8918301","description":"<b>기적의 한글 학습 2 - 기본자 학습 2</b>, <b>개정판</b> ㅣ길벗 <b>기적의</b> <b>학습</b>법 <b>최영환</b> 지음, 천소 그림 / 길벗스쿨... 통문자 <b>학습</b>법이 아닌 훈민정음 창제 원리 방식 <b>학습</b>법으로 쉽고 빠르게 <b>한글</b>을 배울 수 있습니다.... ","bloggername":"[곽혜나님의 서재] \"책과 통하는 블로그, 알라딘 서재!\"","bloggerlink":"https://blog.aladin.co.kr/723159102","postdate":"20161121"},{"title":"20171201 48주 유아","link":"https://blog.aladin.co.kr/741825179/9744687","description":"<b>한글</b>- 개정된 교육과정을 반영한 초등 교과 미리 익히기! 아이세움 편집부 엮음... 구판절판 <b>기적의 한글 학습 2- 기본자 학습 2</b>, <b>개정판 최영환</b> 지음, 천소 그림 / 길벗스쿨 / 2016년 10월 9,000... ","bloggername":"[jkn님의 서재] : 알라딘","bloggerlink":"https://blog.aladin.co.kr/741825179","postdate":"20171201"},{"title":"20171229 52주 유아","link":"https://blog.aladin.co.kr/741825179/9802053","description":"설정순 25개 펼쳐서 보기 처음 | 이전 | 1 | <b>2</b> | 3 | 4 |다음 | 마지막 <b>기적의</b> 파닉스 1 (본책... 저장 <b>기적의 한글 학습 2- 기본자 학습 2</b>, <b>개정판 최영환</b> 지음, 천소 그림 / 길벗스쿨 / 2016년 10월 9... ","bloggername":"[jkn님의 서재] : 알라딘","bloggerlink":"https://blog.aladin.co.kr/741825179","postdate":"20171229"},{"title":"유아,출간1주이내, 평점순. 1p.","link":"https://blog.aladin.co.kr/797342291/15266610","description":"저장 <b>기적의 한글 학습</b> 5- 쌍자음과 <b>한글</b>을 예쁘게 쓰는 순서 1, <b>2</b>, <b>개정판 최영환</b> 지음... 저장 <b>기적의 한글 학습 2- 기본자 학습 2</b>, <b>개정판 최영환</b> 지음, 천소 그림 / 길벗스쿨 / 2024년 2월 11... ","bloggername":"[libjes님의 서재] : 알라딘","bloggerlink":"https://blog.aladin.co.kr/797342291","postdate":"20240131"}]},"timestamp":1770011814886}