{"data":{"lastBuildDate":"Mon, 02 Feb 2026 22:27:49 +0900","total":1,"start":1,"display":1,"items":[{"title":"식물도 움직여?","link":"https://search.shopping.naver.com/book/catalog/32543821782","image":"https://shopping-phinf.pstatic.net/main_3254382/32543821782.20230725120629.jpg","author":"Hirsch, Rebecca E.","discount":"10800","publisher":"현암주니어","pubdate":"20180225","isbn":"9788932374635","description":"식물은 끊임없이 움직이고 있어요!\n\n식물은 움직이지 않는 것처럼 보이지만, 사실은 끊임없이 움직이고 있어요. 아주아주 느리게 움직여서 거의 움직이지 않는 것처럼 보일 뿐이에요. 자세히 들여다보면 모든 식물은 살아가는 데 필요한 물과 햇빛과 자랄 공간을 찾아 다양한 방법으로 움직이고 있답니다. 많은 식물이 햇빛을 향해 잎을 펼쳐 영양분을 만들어요. 나팔꽃처럼 담장을 기어오르며 자라는 식물도 있고, 튤립처럼 밤이면 잠을 자는 식물도 있어요. 특히 씨앗은 아주 활발하게 움직여요. 분출오이처럼 펑 터지면서 멀리 날아가기도 하고, 민들레 씨앗처럼 가벼운 날개를 달고 둥둥 떠다니기도 해요. 열매를 먹은 동물이 똥에 섞여 씨앗을 내보내기도 하지요. 식물은 이처럼 다양한 방법으로 자라고, 또 새로운 생명을 탄생시킨답니다. \n식물을 생생하게 묘사하고 좀 더 자세한 설명을 식물 그림과 함께 볼 수 있도록 정리한 정보 페이지를 덧붙인 그림책입니다. 식물에 관한 지식과 더불어 교과서에서 만나 보게 될 식물에 관한 용어들을 미리 정리해 볼 수 있도록 도와줍니다."}]},"timestamp":1770038868989}