{"data":{"lastBuildDate":"Mon, 02 Feb 2026 22:32:22 +0900","total":1,"start":1,"display":1,"items":[{"title":"피아노 치기는 지겨워","link":"https://search.shopping.naver.com/book/catalog/32466671629","image":"https://shopping-phinf.pstatic.net/main_3246667/32466671629.20241203081506.jpg","author":"다비드 칼리","discount":"7650","publisher":"비룡소","pubdate":"20170410","isbn":"9788949111605","description":"2006년 볼로냐 라가치 상 '새로운 예술상' 부문 수상작! 마르콜리노는 날마다 3시가 되면 피아노를 쳐요. 하지만 피아노 연습은 지겹기만 하죠. 엄마는 훌륭한 피아니스트가 되기 위해서는 연습을 열심히 해야 한대요. 마르콜리노는 피아니스트가 되기 싫은데도 말이에요. 어느 날, 마르콜리노는 할아버지에게 자신의 고민을 털어 놓게 되는데…. \n\n☞『피아노 치기는 두려워』는 어린 시절 피아노 치기를 싫어했던 엄마가 아들에게 피아니스트가 되기를 강요하면서 생긴 갈등을 할아버지가 재치있게 풀어주는 유쾌한 이야기로, 부모들의 잘못된 교육 방법을 깜찍하게 비판하고 있습니다."}]},"timestamp":1770039142819}